README.md
setup.py
syncr.py
syncr.egg-info/PKG-INFO
syncr.egg-info/SOURCES.txt
syncr.egg-info/dependency_links.txt
syncr.egg-info/requires.txt
syncr.egg-info/top_level.txt